[{"username":"Filip123","password":"qwerty","age":33,"isActive":"Yes","date":"12.3.2021"},{"username":"Mihajlovski123","password":"12345","age":23,"isActive":"No","date":"15.1.2011"},{"username":"Bombash","password":"zxcvb","age":12,"isActive":"No","date":"21.2.2027"},{"username":"Simple","password":"password","age":45,"isActive":"Yes","date":"30.7.2001"},{"username":"Kamikaza","password":"password1234","age":17,"isActive":"Yes","date":"02.4.1998"},{"username":"Ljupco321","password":"qwerty123","age":65,"isActive":"No","date":"06.8.1993"},{"username":"Stefani123","password":"123456789","age":54,"isActive":"Yes","date":"28.7.2005"},{"username":"Bazuka","password":"asdfghj","age":51,"isActive":"No","date":"23.6.2031"},{"username":"Bobobo","password":"p@ssw0rd","age":24,"isActive":"Yes","date":"12.3.2102"},{"username":"FASdas","password":"0987654321","age":47,"isActive":"Yes","date":"17.6.1989"}]